mycalc/calculator.py
oss_calc-0.0.1.dist-info/LICENSE
oss_calc-0.0.1.dist-info/METADATA
oss_calc-0.0.1.dist-info/WHEEL
oss_calc-0.0.1.dist-info/top_level.txt
oss_calc-0.0.1.dist-info/RECORD
