Metadata-Version: 2.1
Name: oss-calc
Version: 0.0.1
Summary: nice calculator
Home-page: https://github.com/chunsejin/calc0001
Download-URL: https://github.com/chunsejin/calc0001/
Author: dlawldn
Classifier: Programming Language :: Python :: 3
License-File: LICENSE
